theverse/__init__.py
theverse/cmdline.py
theverse/err.py
theverse/fmtversion.py
theverse/version.py
theverse/classes/__init__.py
theverse/classes/astronomy.py
theverse/classes/base.py
theverse/classes/dimensions.py
theverse/classes/quantity.py
theverse/classes/refstr.py
theverse/data/__init__.py
theverse/data/universe/__init__.py
theverse/data/universe/planetary_systems.py
theverse/data/universe/planets.py
theverse/data/universe/stars.py
theverse-0.1.1.dist-info/LICENSE.txt
theverse-0.1.1.dist-info/METADATA
theverse-0.1.1.dist-info/WHEEL
theverse-0.1.1.dist-info/top_level.txt
theverse-0.1.1.dist-info/RECORD
