Metadata-Version: 2.1
Name: theverse
Version: 0.1.1
Summary: Find properties of objects in our universe (and others) without leaving Python
Home-page: http://github.com/gpoore/theverse
Author: Geoffrey M. Poore
Author-email: gpoore@gmail.com
License: BSD
Keywords: reference,physics,astronomy,chemistry,planetary system,star,planet
Platform: UNKNOWN
Classifier: Development Status :: 4 - Beta
Classifier: Environment :: Console
Classifier: Intended Audience :: Education
Classifier: License :: OSI Approved :: BSD License
Classifier: Operating System :: OS Independent
Classifier: Programming Language :: Python :: 3.6
Classifier: Programming Language :: Python :: 3.7
Classifier: Programming Language :: Python :: 3.8
Classifier: Topic :: Education :: Testing
Requires-Python: >=3.6
